sedatatools/__init__.py
sedatatools/cli.py
sedatatools/sedatatools.py
sedatatools/documentation/Makefile
sedatatools/documentation/__init__.py
sedatatools/documentation/conf.py
sedatatools/documentation/index.rst
sedatatools/documentation/make.bat
sedatatools/facility_tagging/__init__.py
sedatatools/onetimers/__init__.py
sedatatools/onetimers/acs_analyzer.py
sedatatools/tools/__init__.py
sedatatools/tools/connectors/__init__.py
sedatatools/tools/connectors/connectors.py
sedatatools/tools/connectors/prime.py
tests/__init__.py
tests/test_median_cals.py
tests/test_sedatatools.py
tests/helpers/__init__.py
tests/helpers/bracket_calculations/NOT TESTED
tests/helpers/bracket_calculations/__init__.py
tests/helpers/bracket_calculations/median_calculation.py
sedatatools-1.1.5.dist-info/AUTHORS.rst
sedatatools-1.1.5.dist-info/LICENSE
sedatatools-1.1.5.dist-info/METADATA
sedatatools-1.1.5.dist-info/WHEEL
sedatatools-1.1.5.dist-info/entry_points.txt
sedatatools-1.1.5.dist-info/top_level.txt
sedatatools-1.1.5.dist-info/RECORD
