Metadata-Version: 2.1
Name: sedatatools
Version: 1.1.5
Summary: Tools for data team at SE.
Home-page: https://github.com/SocialExplorer/ContentProduction/tree/master/sedatatools
Author: Vedad Ramovic
Author-email: vedad@socialexplorer.com
License: MIT license
Keywords: sedatatools
Platform: UNKNOWN
Classifier: Development Status :: 4 - Beta
Classifier: Intended Audience :: Developers
Classifier: License :: OSI Approved :: MIT License
Classifier: Natural Language :: English
Classifier: Programming Language :: Python :: 3.8
Requires-Python: >=3.8
License-File: LICENSE
License-File: AUTHORS.rst
